unsplash/__init__.py
unsplash/admin.py
unsplash/apps.py
unsplash/forms.py
unsplash/models.py
unsplash/tests.py
unsplash/urls.py
unsplash/views.py
unsplash/migrations/0001_initial.py
unsplash/migrations/0002_auto_20181231_1533.py
unsplash/migrations/0003_slide_background_position_y.py
unsplash/migrations/__init__.py
unsplash/static/unsplash/scss/index.scss
unsplash/static/unsplash/scss/slide-admin.scss
unsplash/templates/includes/image.html
unsplash/templates/includes/parallax.html
unsplash/templates/includes/separator.html
unsplash/templates/includes/slide-admin.html
unsplash/templates/includes/slide.html
unsplash/templates/includes/slideshow.html
unsplash/templates/unsplash/base.html
unsplash/templates/unsplash/index.html
unsplash/templates/unsplash/random_photos.html
unsplash/templatetags/__init__.py
unsplash/templatetags/unsplash_tags.py
unsplash/templatetags/__pycache__/__init__.cpython-35.pyc
unsplash/templatetags/__pycache__/unsplash_tags.cpython-35.pyc
django_unsplash-1.0.dist-info/LICENSE
django_unsplash-1.0.dist-info/METADATA
django_unsplash-1.0.dist-info/WHEEL
django_unsplash-1.0.dist-info/top_level.txt
django_unsplash-1.0.dist-info/RECORD
